{
  "__NAME__": {
    "skip_generation": false,
    "repository": "github.com/terraform-providers/terraform-provider-__NAME__",
    "file": "__NAME__.json",
    "pkg_name": "__NAME__",
    "go_envs": "GO111MODULE=off",
    "provider_args": ""
  },

  "scaffolding": {
    "skip_generation": true
  },
  "oci": {
  },
  "azure": {
    "repository": "github.com/terraform-providers/terraform-provider-azure-classic",
    "pkg_name": "azure"
  },
  "azure-classic" : {
    "skip_generation": true
  },

  "archive": {
  },
  "cloudinit": {
    "repository": "github.com/hashicorp/terraform-provider-__NAME__"
  },
  "dns": {
    "repository": "github.com/hashicorp/terraform-provider-__NAME__"
  },
  "external": {
  },
  "http": {
  },
  "local": {
  },
  "null": {
    "repository": "github.com/hashicorp/terraform-provider-__NAME__"
  },
  "random": {
    "repository": "github.com/hashicorp/terraform-provider-__NAME__"
  },
  "template": {
    "repository": "github.com/hashicorp/terraform-provider-__NAME__"
  },
  "terraform": {
    "skip_generation": true,
    "pkg_name": "builtin/providers/__NAME__",
    "repository": "github.com/hashicorp/terraform"
  },
  "test": {
    "pkg_name": "builtin/providers/__NAME__",
    "repository": "github.com/hashicorp/terraform"
  },
  "time": {
    "pkg_name": "internal/tftime",
    "repository": "github.com/hashicorp/terraform-provider-__NAME__"
  },
  "tls": {
    "repository": "github.com/hashicorp/terraform-provider-__NAME__"
  },

  "aci": {},
  "acme": {},
  "akamai": {},
  "alicloud": {},
  "arukas": {},
  "auth0": {},
  "avi": {},
  "aviatrix": {},
  "aws": {},
  "azuread": {},
  "azuredevops": {},
  "azurerm": {},
  "azurestack": {},
  "baiducloud": {},
  "bigip": {},
  "bitbucket": {},
  "brightbox": {},
  "checkpoint": {},
  "chef": {},
  "cherryservers": {},
  "circonus": {},
  "ciscoasa": {},
  "clc": {},
  "cloudamqp": {},
  "cloudflare": {},
  "cloudscale": {},
  "cloudstack": {},
  "cobbler": {},
  "cohesity" : {},
  "constellix" : {},
  "consul": {},
  "datadog": {},
  "digitalocean": {},
  "dme": {},
  "dnsimple": {},
  "docker": {},
  "dome9": {},
  "dyn": {},
  "ecl" : {
    "go_envs": "GO111MODULE=on"
  },
  "exoscale": {},
  "fastly": {},
  "flexibleengine": {},
  "fortios": {},
  "genymotion": {},
  "github": {},
  "gitlab": {},
  "google": {},
  "google-beta": {},
  "grafana": {},
  "gridscale": {},
  "hashicups": {
    "repository": "github.com/hashicorp/terraform-provider-__NAME__",
    "go_envs": "GO111MODULE=on"
  },
  "hcloud": {},
  "hedvig": {},
  "helm": {},
  "heroku": {},
  "huaweicloud": {},
  "huaweicloudstack": {},
  "icinga2": {},
  "ignition": {},
  "incapsula": {},
  "influxdb": {},
  "infoblox": {},
  "jdcloud": {},
  "ksyun" : {},
  "kubernetes": {},
  "kubernetes-alpha" : {
    "pkg_name": "provider",
    "repository": "github.com/hashicorp/terraform-provider-__NAME__"
  },
  "lacework" : {},
  "launchdarkly": {},
  "librato": {},
  "linode": {},
  "logentries": {},
  "logicmonitor": {},
  "mailgun": {},
  "metalcloud": {},
  "mongodbatlas": {},
  "mso": {},
  "mysql": {},
  "ncloud": {},
  "netlify": {},
  "newrelic": {},
  "nks": {},
  "nomad": {},
  "ns1": {},
  "nsxt": {},
  "nutanix": {},
  "okta": {},
  "oktaasa": {},
  "oneandone": {},
  "opc": {},
  "opennebula": {},
  "openstack": {},
  "opentelekomcloud": {},
  "opsgenie": {},
  "oraclepaas": {},
  "ovh": {},
  "packet": {},
  "pagerduty": {},
  "panos": {},
  "postgresql": {},
  "powerdns": {},
  "prismacloud": {},
  "profitbricks": {},
  "pureport": {},
  "rabbitmq": {},
  "rancher": {},
  "rancher2": {},
  "rightscale": {},
  "rubrik": {},
  "rundeck": {},
  "runscope": {},
  "scaleway": {},
  "selectel": {},
  "signalfx": {},
  "skytap": {},
  "softlayer": {},
  "spotinst": {},
  "stackpath": {},
  "statuscake": {},
  "sumologic": {},
  "telefonicaopencloud": {},
  "tencentcloud": {},
  "tfe": {},
  "triton": {},
  "turbot": {},
  "ucloud": {},
  "ultradns": {},
  "vault": {},
  "vcd": {},
  "venafi": {},
  "vmc": {},
  "vra7": {},
  "vsphere": {
    "repository": "github.com/hashicorp/terraform-provider-__NAME__",
    "go_envs": "GO111MODULE=on"
  },
  "vthunder": {},
  "vultr": {},
  "wavefront" : {},
  "yandex": {}
}